varray/__init__.py
varray/_utils.py
varray/_version.py
varray/varray_class.py
varray/varray_creation.py
varray/varray_manipulation.py
varray-1.1.5.dist-info/licenses/LICENSE
varray-1.1.5.dist-info/METADATA
varray-1.1.5.dist-info/WHEEL
varray-1.1.5.dist-info/top_level.txt
varray-1.1.5.dist-info/RECORD
