Metadata-Version: 2.4
Name: varray
Version: 1.1.5
Summary: A numpy-like array object with variable-length rows
Author-email: "Aaron M." <aaronm6@gmail.com>
License-Expression: BSD-3-Clause
Project-URL: Homepage, https://github.com/aaronm6/varray
Project-URL: Repository, https://github.com/aaronm6/varray
Platform: unix-like
Classifier: Programming Language :: Python :: 3
Requires-Python: >=3.9.0
License-File: LICENSE
Requires-Dist: numpy>=1.26.0
Dynamic: license-file
